{"name":"WakeUp Labs","description":"WakeUp Labs is a start-up that aims to lower the barriers for the integration of web3 features into web2 businesses and projects. The company provides a platform that enables developers, without previous blockchain experience, to integrate web3 features with ease and speed by offering REST APIs for straightforward integration. It offers full compatibility with the Optimism blockchain and others.","category":"Tooling and utilities","votedominance":"0.1133","totalop":"11,328.63"}