[{"name":"raho & tnorm","value":10},{"name":"Optimism Grant Analytics: Grant3","value":5},{"name":"European Crypto Initiative","value":4},{"name":"HER LATAM _ Optimistas Brillando en Blockchain","value":13},{"name":"Public HAUS","value":9},{"name":"Subli","value":7},{"name":"Builder Protocol","value":11},{"name":"Optimism Community Governance Calls (Michael)","value":19},{"name":"Metagov","value":10},{"name":"ITU Blockchain","value":12},{"name":"Hats Protocol","value":10},{"name":"Xanny","value":5},{"name":"Tally","value":15},{"name":"Agora","value":23},{"name":"Optimism Grants Council Season 4","value":12},{"name":"Web3Native","value":2},{"name":"Optimism Resource Center","value":13},{"name":"Flexible Voting","value":7},{"name":"polynya","value":22},{"name":"EIP-4824/ DAOstar","value":6},{"name":"Boardroom","value":11},{"name":"Giveth","value":17},{"name":"satorrr","value":9},{"name":"SEED Latam","value":17},{"name":"Coordinape","value":10},{"name":"Retrolist | RetroPGF Rubric-based List Creation UI","value":7},{"name":"Optimism Grants Changelog","value":11},{"name":"RegenScore","value":8},{"name":"OP Governance Analytics Dashboard","value":13},{"name":"Gravity DAO","value":8},{"name":"Commons Stack","value":8},{"name":"Gitcoin","value":19},{"name":"Pairwise","value":14},{"name":"LauNaMu","value":18},{"name":"Public Goods Grant Management","value":2},{"name":"Praise","value":18},{"name":"Mechanism Institute","value":7},{"name":"Josh | The Blockchain Socialist","value":5},{"name":"Snapshot","value":16},{"name":"RetroPGF Hub","value":15},{"name":"CharmVerse","value":14},{"name":"Open Source Observer","value":15},{"name":"RadicalxChange Foundation","value":12},{"name":"Gov","value":4},{"name":"Hypercerts Foundation","value":10},{"name":"webOfTrust","value":10},{"name":"OP Security Council Rehearsal Beta Testers","value":2},{"name":"Karma","value":16}]