{"name":"rotki","description":"rotki is an open source portfolio tracking, analytics & accounting tool that protects your privacy. The mission of rotki is to bring transparency for crypto through the use of open source. Unlike virtually every other competing service which consists of closed source SaaS onto which you are forced to hand over all your financial data, with rotki your data is stored encrypted locally.","category":"Tooling and utilities","votedominance":"1.4527","totalop":"145,272.64"}